atgfe/GeneticFeatureEngineer.py
atgfe/GeneticFeatureEngineerWithoutBraces.py
atgfe/__init__.py
atgfe/single_operation_functions.py
atgfe-0.2.60.dist-info/LICENSE
atgfe-0.2.60.dist-info/WHEEL
atgfe-0.2.60.dist-info/METADATA
atgfe-0.2.60.dist-info/RECORD
