Metadata-Version: 2.1
Name: atgfe
Version: 0.2.60
Summary: Automated Transparent Genetic Feature Engineering or ATgfe
Home-page: https://github.com/ahmed-mohamed-sn/ATgfe
License: MIT
Keywords: Python,Machine Learning,Feature Engineering,Genetic Algorithms,Explainable
Author: ahmed-mohamed-sn
Author-email: hanoush87@gmail.com
Requires-Python: >=3.6,<4.0
Classifier: Intended Audience :: Customer Service
Classifier: Intended Audience :: Developers
Classifier: Intended Audience :: Financial and Insurance Industry
Classifier: Intended Audience :: Healthcare Industry
Classifier: Intended Audience :: Legal Industry
Classifier: Intended Audience :: Other Audience
Classifier: Intended Audience :: Science/Research
Classifier: License :: OSI Approved :: MIT License
Classifier: Operating System :: OS Independent
Classifier: Programming Language :: Python :: 3
Classifier: Programming Language :: Python :: 3.6
Classifier: Programming Language :: Python :: 3.7
Classifier: Topic :: Scientific/Engineering :: Artificial Intelligence
Requires-Dist: deap (>=1.3,<2.0)
Requires-Dist: numpy (>=1.17,<2.0)
Requires-Dist: pandas (>=0.25.2,<0.26.0)
Requires-Dist: scipy (>=1.3,<2.0)
Requires-Dist: sympy (>=1.4,<2.0)
Project-URL: Repository, https://github.com/ahmed-mohamed-sn/ATgfe
